Metadata-Version: 2.1
Name: odoo12-addon-report_async
Version: 12.0.2.0.0
Summary: Central place to run reports live or async
Home-page: https://github.com/OCA/reporting-engine
Author: Ecosoft, Odoo Community Association (OCA)
Author-email: support@odoo-community.org
License: AGPL-3
Classifier: Programming Language :: Python
Classifier: Framework :: Odoo
Classifier: Framework :: Odoo :: 12.0
Classifier: License :: OSI Approved :: GNU Affero General Public License v3
Classifier: Development Status :: 4 - Beta
Requires-Python: >=3.5
Requires-Dist: odoo12-addon-queue-job
Requires-Dist: odoo <12.1dev,>=12.0a
